Workbook

Sheet Raw Data
A1: Order_ID | B1: Order_Date | C1: Region | D1: Product | E1: Category | F1: Sales_Amount | G1: Profit | H1: Quantity | J1: Note: Raw export — contains duplicate rows, missing Region/Category values, and inconsistent date formats.
A2: ORD1001 | B2: 03-04-2026 | C2: East | D2: ProBook X1 | E2: Laptops | F2: 850 | G2: 119.0 | H2: 1
A3: ORD1002 | B3: 2026-03-01 | C3: South | D3: ProBook X1 | E3: Laptops | F3: 850 | G3: 239.11 | H3: 1
A4: ORD1003 | B4: 2026-01-02 | C4: East | D4: Laptop Sleeve 14in | E4: Accessories | F4: 20 | G4: 6.23 | H4: 2
A5: ORD1004 | B5: 08/04/2026 | C5: North | D5: SoundWave Buds | F5: 45 | G5: 50.78 | H5: 5
A6: ORD1005 | B6: 2026-06-10 | C6: East | D6: FastCharge 65W | E6: Accessories | F6: 25 | G6: 9.79 | H6: 3
A7: ORD1006 | B7: 2026-01-26 | C7: South | D7: SoundWave Buds | E7: Audio | F7: 45 | G7: 36.93 | H7: 4
A8: ORD1007 | B8: 2026-06-05 | C8: North | D8: SoundWave Buds Pro | E8: Audio | F8: 65 | G8: 67.36 | H8: 5
A9: ORD1008 | B9: 2026-01-15 | C9: East | D9: FitTrack Band | E9: Wearables | F9: 55 | G9: 54.45 | H9: 3
A10: ORD1009 | B10: 2026-04-12 | C10: West | D10: SoundWave Buds | E10: Audio | F10: 45 | G10: 47.72 | H10: 6
A11: ORD1010 | B11: 2026-05-30 | C11: West | D11: SoundWave Buds Pro | E11: Audio | F11: 65 | G11: 30.36 | H11: 2
A12: ORD1011 | B12: 2026-06-24 | C12: South | D12: UltraSlim 14 | E12: Laptops | F12: 720 | G12: 163.91 | H12: 1
A13: ORD1012 | B13: 2026-06-24 | C13: North | D13: FitTrack Band | E13: Wearables | F13: 55 | G13: 30.94 | H13: 3
A14: ORD1013 | B14: 2026-05-10 | C14: South | D14: GameForce G5 | E14: Laptops | F14: 1200 | G14: 1872.45 | H14: 6
A15: ORD1014 | B15: 06/05/2026 | C15: East | D15: NovaPhone 12 | E15: Smartphones | F15: 620 | G15: 465.92 | H15: 3
A16: ORD1015 | B16: 2026-02-02 | C16: South | D16: FastCharge 65W | E16: Accessories | F16: 25 | G16: 32.44 | H16: 5
A17: ORD1016 | B17: 2026-04-13 | C17: East | D17: FitTrack Band | E17: Wearables | F17: 55 | G17: 73.87 | H17: 6
... A47: ORD1041 | B47: 2026-06-20 | C47: East | D47: SoundWave Buds Pro | E47: Audio | F47: 65 | G47: 42.67 | H47: 4
A48: ORD1042 | B48: 2026-06-07 | C48: South | D48: Laptop Sleeve 14in | F48: 20 | G48: 14.88 | H48: 4
A49: ORD1043 | B49: 2026-04-24 | C49: West | D49: FitTrack Watch Pro | E49: Wearables | F49: 130 | G49: 88.6 | H49: 2
A50: ORD1044 | B50: 2026-01-24 | C50: East | D50: GameForce G5 | E50: Laptops | F50: 1200 | G50: 397.92 | H50: 2
A51: ORD1044 | B51: 2026-01-24 | C51: East | D51: GameForce G5 | E51: Laptops | F51: 1200 | G51: 397.92 | H51: 2
A52: ORD1045 | B52: 2026-04-27 | C52: North | D52: NovaPhone 12 Pro | E52: Smartphones | F52: 780 | G52: 974.91 | H52: 6
A53: ORD1046 | B53: 04-19-2026 | C53: North | D53: NovaPhone 12 | E53: Smartphones | F53: 620 | G53: 1026.16 | H53: 5
A54: ORD1047 | B54: 2026-04-24 | C54: East | D54: NovaPhone 12 Pro | E54: Smartphones | F54: 780 | G54: 1537.74 | H54: 6
A55: ORD1048 | B55: 2026-03-08 | C55: West | D55: NovaPhone 12 Pro | E55: Smartphones | F55: 780 | G55: 1083.22 | H55: 6
A56: ORD1049 | B56: 2026-03-02 | C56: East | D56: FastCharge 65W | E56: Accessories | F56: 25 | G56: 11.6 | H56: 3
A57: ORD1050 | B57: 2026-04-17 | C57: North | D57: PixelMax S | E57: Smartphones | F57: 590 | G57: 919.12 | H57: 5
A58: ORD1051 | B58: 03/05/2026 | C58: West | D58: FitTrack Band | E58: Wearables | F58: 55 | G58: 55.98 | H58: 3
A59: ORD1052 | B59: 2026-02-26 | D59: FitTrack Band | E59: Wearables | F59: 55 | G59: 60.76 | H59: 4
A60: ORD1053 | B60: 2026-06-09 | C60: South | D60: NovaPhone 12 Pro | E60: Smartphones | F60: 780 | G60: 434.64 | H60: 4
A61: ORD1054 | B61: 2026-03-08 | C61: North | D61: FastCharge 65W | E61: Accessories | F61: 25 | G61: 16.12 | H61: 2
A62: ORD1055 | B62: 05-01-2026 | C62: North | D62: TypeC Cable Pack | E62: Accessories | F62: 12 | G62: 3.23 | H62: 1
A63: ORD1056 | B63: 2026-02-21 | C63: South | D63: ProBook X1 | E63: Laptops | F63: 850 | G63: 1164.4 | H63: 5
A64: ORD1057 | B64: 04-05-2026 | C64: East | D64: NovaPhone 12 Pro | E64: Smartphones | F64: 780 | G64: 737.88 | H64: 6
A65: ORD1058 | B65: 2026-05-28 | C65: East | D65: FitTrack Band | E65: Wearables | F65: 55 | G65: 30.25 | H65: 4
A66: ORD1059 | B66: 2026-06-25 | C66: East | D66: NovaPhone 12 | E66: Smartphones | F66: 620 | G66: 80.26 | H66: 1
A67: ORD1060 | B67: 2026-01-04 | C67: East | D67: SoundWave Buds | E67: Audio | F67: 45 | G67: 47.91 | H67: 4
A68: ORD1061 | B68: 2026-05-14 | C68: South | D68: NovaPhone 12 Pro | E68: Smartphones | F68: 780 | G68: 697.71 | H68: 3
A69: ORD1062 | B69: 2026-03-04 | C69: East | D69: FitTrack Watch Pro | E69: Wearables | F69: 130 | G69: 38.04 | H69: 1
A70: ORD1063 | B70: 2026-05-07 | C70: North | D70: TypeC Cable Pack | E70: Accessories | F70: 12 | G70: 4.31 | H70: 2
A71: ORD1064 | B71: 2026-05-13 | C71: North | D71: FitTrack Watch Pro | E71: Wearables | F71: 130 | G71: 32.2 | H71: 1
... A74: ORD1067 | B74: 2026-01-31 | C74: East | D74: UltraSlim 14 | E74: Laptops | F74: 720 | G74: 999.5 | H74: 6
A75: ORD1068 | B75: 2026-02-19 | C75: North | D75: FitTrack Watch Pro | F75: 130 | G75: 94.71 | H75: 3
A76: ORD1069 | B76: 2026-06-13 | C76: South | D76: GameForce G5 | F76: 1200 | G76: 889.91 | H76: 4
A77: ORD1070 | B77: 2026-03-06 | C77: North | D77: SoundWave Buds | E77: Audio | F77: 45 | G77: 41.96 | H77: 4
A78: ORD1071 | B78: 2026-05-25 | C78: South | D78: UltraSlim 14 | E78: Laptops | F78: 720 | G78: 212.99 | H78: 1
A79: ORD1072 | B79: 2026-04-26 | C79: West | D79: FitTrack Band | E79: Wearables | F79: 55 | G79: 31.39 | H79: 3
A80: ORD1073 | B80: 06-10-2026 | C80: South | D80: FitTrack Band | E80: Wearables | F80: 55 | G80: 7.55 | H80: 1
A81: ORD1073 | B81: 06-10-2026 | C81: South | D81: FitTrack Band | E81: Wearables | F81: 55 | G81: 7.55 | H81: 1
A82: ORD1074 | B82: 16/03/2026 | C82: West | D82: Laptop Sleeve 14in | E82: Accessories | F82: 20 | G82: 16.36 | H82: 6
A83: ORD1075 | B83: 2026-04-19 | C83: South | D83: SoundWave Buds Pro | E83: Audio | F83: 65 | G83: 59.56 | H83: 6
A84: ORD1076 | B84: 04-23-2026 | C84: East | D84: SoundWave Buds Pro | E84: Audio | F84: 65 | G84: 45.85 | H84: 3
A85: ORD1077 | B85: 2026-03-24 | C85: West | D85: ProBook X1 | E85: Laptops | F85: 850 | G85: 265.43 | H85: 1
A86: ORD1078 | B86: 2026-02-14 | C86: North | D86: GameForce G5 | E86: Laptops | F86: 1200 | G86: 2514.94 | H86: 6
A87: ORD1079 | B87: 2026-03-31 | C87: West | D87: FastCharge 65W | E87: Accessories | F87: 25 | G87: 14.69 | H87: 3
A88: ORD1080 | B88: 2026-05-21 | C88: West | D88: SoundWave Buds Pro | E88: Audio | F88: 65 | G88: 58.05 | H88: 3
... A95: ORD1086 | B95: 2026-02-08 | C95: West | D95: SoundWave Buds Pro | E95: Audio | F95: 65 | G95: 63.7 | H95: 4
A96: ORD1087 | B96: 2026-05-27 | D96: SoundWave Buds | E96: Audio | F96: 45 | G96: 50.8 | H96: 4
A97: ORD1088 | B97: 2026-05-07 | C97: South | D97: Laptop Sleeve 14in | E97: Accessories | F97: 20 | G97: 12.8 | H97: 2
A98: ORD1089 | B98: 2026-01-04 | C98: West | D98: FastCharge 65W | E98: Accessories | F98: 25 | G98: 13.72 | H98: 4
A99: ORD1090 | B99: 16/06/2026 | C99: West | D99: BassPod Speaker | E99: Audio | F99: 90 | G99: 104.13 | H99: 6
A100: ORD1091 | B100: 06-08-2026 | C100: North | D100: Laptop Sleeve 14in | E100: Accessories | F100: 20 | G100: 35.01 | H100: 6
A101: ORD1092 | B101: 2026-02-12 | D101: ProBook X1 | E101: Laptops | F101: 850 | G101: 159.35 | H101: 1
A102: ORD1093 | B102: 2026-05-25 | C102: West | D102: PixelMax S | E102: Smartphones | F102: 590 | G102: 377.95 | H102: 2
A103: ORD1094 | B103: 2026-03-01 | C103: South | D103: NovaPhone 12 Pro | E103: Smartphones | F103: 780 | G103: 764.59 | H103: 3
A104: ORD1095 | B104: 2026-01-19 | C104: South | D104: SoundWave Buds Pro | E104: Audio | F104: 65 | G104: 66.55 | H104: 3
A105: ORD1096 | B105: 2026-04-09 | C105: South | D105: TypeC Cable Pack | E105: Accessories | F105: 12 | G105: 3.03 | H105: 1
A106: ORD1097 | B106: 03-12-2026 | C106: West | D106: SoundWave Buds | E106: Audio | F106: 45 | G106: 78.68 | H106: 6
A107: ORD1098 | B107: 2026-02-26 | C107: East | D107: SoundWave Buds | E107: Audio | F107: 45 | G107: 66.72 | H107: 5
A108: ORD1099 | B108: 2026-03-21 | C108: North | D108: NovaPhone 12 | E108: Smartphones | F108: 620 | G108: 87.25 | H108: 1
A109: ORD1100 | B109: 2026-02-03 | C109: South | D109: FastCharge 65W | E109: Accessories | F109: 25 | G109: 23.33 | H109: 3
A110: ORD1101 | B110: 2026-01-30 | C110: East | D110: TypeC Cable Pack | E110: Accessories | F110: 12 | G110: 3.81 | H110: 1
A111: ORD1102 | B111: 2026-01-24 | C111: East | D111: Laptop Sleeve 14in | E111: Accessories | F111: 20 | G111: 4.1 | H111: 1
A112: ORD1103 | B112: 2026-06-13 | C112: West | D112: SoundWave Buds Pro | E112: Audio | F112: 65 | G112: 17.06 | H112: 1
A113: ORD1104 | B113: 15/06/2026 | C113: South | D113: SoundWave Buds Pro | E113: Audio | F113: 65 | G113: 59.34 | H113: 6
... A163: ORD1153 | B163: 2026-06-20 | C163: South | D163: FitTrack Watch Pro | E163: Wearables | F163: 130 | G163: 156.65 | H163: 5
A164: ORD1154 | B164: 01/05/2026 | C164: West | D164: FitTrack Band | F164: 55 | G164: 49.72 | H164: 3
A165: ORD1155 | B165: 2026-01-12 | C165: South | D165: GameForce G5 | E165: Laptops | F165: 1200 | G165: 1077.13 | H165: 3
A166: ORD1156 | B166: 04/02/2026 | C166: South | D166: Laptop Sleeve 14in | F166: 20 | G166: 3.32 | H166: 1
A167: ORD1156 | B167: 04/02/2026 | C167: South | D167: Laptop Sleeve 14in | F167: 20 | G167: 3.32 | H167: 1
A168: ORD1157 | B168: 2026-05-20 | C168: West | D168: SoundWave Buds Pro | E168: Audio | F168: 65 | G168: 13.14 | H168: 1
A169: ORD1158 | B169: 2026-04-05 | C169: North | D169: BassPod Speaker | E169: Audio | F169: 90 | G169: 75.21 | H169: 4
A170: ORD1159 | B170: 2026-04-05 | C170: West | D170: Laptop Sleeve 14in | E170: Accessories | F170: 20 | G170: 21.76 | H170: 5
A171: ORD1160 | B171: 01-27-2026 | C171: East | D171: OrbitPhone Lite | E171: Smartphones | F171: 310 | G171: 202.75 | H171: 3

Sheet Cleaned Data
A1: Order_ID | B1: Order_Date | C1: Region | D1: Product | E1: Category | F1: Unit_Price | G1: Profit | H1: Quantity | I1: Total_Sales | J1: Profit_Margin
A2: ORD1001 | B2: 46085 | C2: East | D2: ProBook X1 | E2: Laptops | F2: 850 | G2: 119 | H2: 1 | I2: =F2*H2 -> 850 | J2: =IF(I2=0,0,G2/I2) -> 0.14
A3: ORD1002 | B3: 46082 | C3: South | D3: ProBook X1 | E3: Laptops | F3: 850 | G3: 239.11 | H3: 1 | I3: =F3*H3 -> 850 | J3: =IF(I3=0,0,G3/I3) -> 0.28130588
A4: ORD1003 | B4: 46024 | C4: East | D4: Laptop Sleeve 14in | E4: Accessories | F4: 20 | G4: 6.23 | H4: 2 | I4: =F4*H4 -> 40 | J4: =IF(I4=0,0,G4/I4) -> 0.15575
A5: ORD1004 | B5: 46120 | C5: North | D5: SoundWave Buds | E5: Audio | F5: 45 | G5: 50.78 | H5: 5 | I5: =F5*H5 -> 225 | J5: =IF(I5=0,0,G5/I5) -> 0.22568889
A6: ORD1005 | B6: 46183 | C6: East | D6: FastCharge 65W | E6: Accessories | F6: 25 | G6: 9.79 | H6: 3 | I6: =F6*H6 -> 75 | J6: =IF(I6=0,0,G6/I6) -> 0.13053333
A7: ORD1006 | B7: 46048 | C7: South | D7: SoundWave Buds | E7: Audio | F7: 45 | G7: 36.93 | H7: 4 | I7: =F7*H7 -> 180 | J7: =IF(I7=0,0,G7/I7) -> 0.20516667
A8: ORD1007 | B8: 46178 | C8: North | D8: SoundWave Buds Pro | E8: Audio | F8: 65 | G8: 67.36 | H8: 5 | I8: =F8*H8 -> 325 | J8: =IF(I8=0,0,G8/I8) -> 0.20726154
A9: ORD1008 | B9: 46037 | C9: East | D9: FitTrack Band | E9: Wearables | F9: 55 | G9: 54.45 | H9: 3 | I9: =F9*H9 -> 165 | J9: =IF(I9=0,0,G9/I9) -> 0.33
A10: ORD1009 | B10: 46124 | C10: West | D10: SoundWave Buds | E10: Audio | F10: 45 | G10: 47.72 | H10: 6 | I10: =F10*H10 -> 270 | J10: =IF(I10=0,0,G10/I10) -> 0.17674074
A11: ORD1010 | B11: 46172 | C11: West | D11: SoundWave Buds Pro | E11: Audio | F11: 65 | G11: 30.36 | H11: 2 | I11: =F11*H11 -> 130 | J11: =IF(I11=0,0,G11/I11) -> 0.23353846
A12: ORD1011 | B12: 46197 | C12: South | D12: UltraSlim 14 | E12: Laptops | F12: 720 | G12: 163.91 | H12: 1 | I12: =F12*H12 -> 720 | J12: =IF(I12=0,0,G12/I12) -> 0.22765278
A13: ORD1012 | B13: 46197 | C13: North | D13: FitTrack Band | E13: Wearables | F13: 55 | G13: 30.94 | H13: 3 | I13: =F13*H13 -> 165 | J13: =IF(I13=0,0,G13/I13) -> 0.18751515
... A161: ORD1160 | B161: 46049 | C161: East | D161: OrbitPhone Lite | E161: Smartphones | F161: 310 | G161: 202.75 | H161: 3 | I161: =F161*H161 -> 930 | J161: =IF(I161=0,0,G161/I161) -> 0.21801075

Sheet Dashboard
B2: TechRetail Solutions — Sales Performance Dashboard
B4: Total Revenue | D4: Total Profit | F4: Total Orders | H4: Avg Order Value | J4: Overall Profit Margin
B5: =SUM('Cleaned Data'!I2:I161) -> 171284 | D5: =SUM('Cleaned Data'!G2:G161) -> 43547.95 | F5: =COUNTA('Cleaned Data'!A2:A161) -> 160 | H5: =B5/F5 -> 1070.525 | J5: =D5/B5 -> 0.25424412

Sheet Pivot - By Region
A1: Region | B1: Total Sales | C1: Total Profit | D1: Profit Margin | E1: Order Count
A2: East | B2: =SUMIF('Cleaned Data'!$C$2:$C$161,A2,'Cleaned Data'!$I$2:$I$161) -> 55454 | C2: =SUMIF('Cleaned Data'!$C$2:$C$161,A2,'Cleaned Data'!$G$2:$G$161) -> 13605.36 | D2: =C2/B2 -> 0.24534497 | E2: =COUNTIF('Cleaned Data'!$C$2:$C$161,A2) -> 46
A3: North | B3: =SUMIF('Cleaned Data'!$C$2:$C$161,A3,'Cleaned Data'!$I$2:$I$161) -> 39486 | C3: =SUMIF('Cleaned Data'!$C$2:$C$161,A3,'Cleaned Data'!$G$2:$G$161) -> 11142.33 | D3: =C3/B3 -> 0.28218432 | E3: =COUNTIF('Cleaned Data'!$C$2:$C$161,A3) -> 35
A4: South | B4: =SUMIF('Cleaned Data'!$C$2:$C$161,A4,'Cleaned Data'!$I$2:$I$161) -> 53847 | C4: =SUMIF('Cleaned Data'!$C$2:$C$161,A4,'Cleaned Data'!$G$2:$G$161) -> 12892.52 | D4: =C4/B4 -> 0.23942875 | E4: =COUNTIF('Cleaned Data'!$C$2:$C$161,A4) -> 39
A5: West | B5: =SUMIF('Cleaned Data'!$C$2:$C$161,A5,'Cleaned Data'!$I$2:$I$161) -> 22497 | C5: =SUMIF('Cleaned Data'!$C$2:$C$161,A5,'Cleaned Data'!$G$2:$G$161) -> 5907.74 | D5: =C5/B5 -> 0.26260124 | E5: =COUNTIF('Cleaned Data'!$C$2:$C$161,A5) -> 40

Sheet Pivot - By Product
A1: Product | B1: Category | C1: Total Sales | D1: Total Profit | E1: Units Sold
A2: BassPod Speaker | B2: Audio | C2: =SUMIF('Cleaned Data'!$D$2:$D$161,A2,'Cleaned Data'!$I$2:$I$161) -> 2790 | D2: =SUMIF('Cleaned Data'!$D$2:$D$161,A2,'Cleaned Data'!$G$2:$G$161) -> 630.12 | E2: =SUMIF('Cleaned Data'!$D$2:$D$161,A2,'Cleaned Data'!$H$2:$H$161) -> 31
A3: EliteBook 360 | B3: Laptops | C3: =SUMIF('Cleaned Data'!$D$2:$D$161,A3,'Cleaned Data'!$I$2:$I$161) -> 10780 | D3: =SUMIF('Cleaned Data'!$D$2:$D$161,A3,'Cleaned Data'!$G$2:$G$161) -> 2921.17 | E3: =SUMIF('Cleaned Data'!$D$2:$D$161,A3,'Cleaned Data'!$H$2:$H$161) -> 11
A4: FastCharge 65W | B4: Accessories | C4: =SUMIF('Cleaned Data'!$D$2:$D$161,A4,'Cleaned Data'!$I$2:$I$161) -> 1075 | D4: =SUMIF('Cleaned Data'!$D$2:$D$161,A4,'Cleaned Data'!$G$2:$G$161) -> 241.26 | E4: =SUMIF('Cleaned Data'!$D$2:$D$161,A4,'Cleaned Data'!$H$2:$H$161) -> 43
A5: FitTrack Band | B5: Wearables | C5: =SUMIF('Cleaned Data'!$D$2:$D$161,A5,'Cleaned Data'!$I$2:$I$161) -> 3025 | D5: =SUMIF('Cleaned Data'!$D$2:$D$161,A5,'Cleaned Data'!$G$2:$G$161) -> 704.88 | E5: =SUMIF('Cleaned Data'!$D$2:$D$161,A5,'Cleaned Data'!$H$2:$H$161) -> 55
A6: FitTrack Watch Pro | B6: Wearables | C6: =SUMIF('Cleaned Data'!$D$2:$D$161,A6,'Cleaned Data'!$I$2:$I$161) -> 2340 | D6: =SUMIF('Cleaned Data'!$D$2:$D$161,A6,'Cleaned Data'!$G$2:$G$161) -> 568.63 | E6: =SUMIF('Cleaned Data'!$D$2:$D$161,A6,'Cleaned Data'!$H$2:$H$161) -> 18
A7: GameForce G5 | B7: Laptops | C7: =SUMIF('Cleaned Data'!$D$2:$D$161,A7,'Cleaned Data'!$I$2:$I$161) -> 58800 | D7: =SUMIF('Cleaned Data'!$D$2:$D$161,A7,'Cleaned Data'!$G$2:$G$161) -> 15266.84 | E7: =SUMIF('Cleaned Data'!$D$2:$D$161,A7,'Cleaned Data'!$H$2:$H$161) -> 49
A8: Laptop Sleeve 14in | B8: Accessories | C8: =SUMIF('Cleaned Data'!$D$2:$D$161,A8,'Cleaned Data'!$I$2:$I$161) -> 960 | D8: =SUMIF('Cleaned Data'!$D$2:$D$161,A8,'Cleaned Data'!$G$2:$G$161) -> 198.83 | E8: =SUMIF('Cleaned Data'!$D$2:$D$161,A8,'Cleaned Data'!$H$2:$H$161) -> 48
A9: NovaPhone 12 | B9: Smartphones | C9: =SUMIF('Cleaned Data'!$D$2:$D$161,A9,'Cleaned Data'!$I$2:$I$161) -> 9300 | D9: =SUMIF('Cleaned Data'!$D$2:$D$161,A9,'Cleaned Data'!$G$2:$G$161) -> 2650.14 | E9: =SUMIF('Cleaned Data'!$D$2:$D$161,A9,'Cleaned Data'!$H$2:$H$161) -> 15
A10: NovaPhone 12 Pro | B10: Smartphones | C10: =SUMIF('Cleaned Data'!$D$2:$D$161,A10,'Cleaned Data'!$I$2:$I$161) -> 39000 | D10: =SUMIF('Cleaned Data'!$D$2:$D$161,A10,'Cleaned Data'!$G$2:$G$161) -> 9474.05 | E10: =SUMIF('Cleaned Data'!$D$2:$D$161,A10,'Cleaned Data'!$H$2:$H$161) -> 50
A11: OrbitPhone Lite | B11: Smartphones | C11: =SUMIF('Cleaned Data'!$D$2:$D$161,A11,'Cleaned Data'!$I$2:$I$161) -> 6200 | D11: =SUMIF('Cleaned Data'!$D$2:$D$161,A11,'Cleaned Data'!$G$2:$G$161) -> 1484.35 | E11: =SUMIF('Cleaned Data'!$D$2:$D$161,A11,'Cleaned Data'!$H$2:$H$161) -> 20
A12: PixelMax S | B12: Smartphones | C12: =SUMIF('Cleaned Data'!$D$2:$D$161,A12,'Cleaned Data'!$I$2:$I$161) -> 11210 | D12: =SUMIF('Cleaned Data'!$D$2:$D$161,A12,'Cleaned Data'!$G$2:$G$161) -> 3250.76 | E12: =SUMIF('Cleaned Data'!$D$2:$D$161,A12,'Cleaned Data'!$H$2:$H$161) -> 19
A13: ProBook X1 | B13: Laptops | C13: =SUMIF('Cleaned Data'!$D$2:$D$161,A13,'Cleaned Data'!$I$2:$I$161) -> 8500 | D13: =SUMIF('Cleaned Data'!$D$2:$D$161,A13,'Cleaned Data'!$G$2:$G$161) -> 2136.99 | E13: =SUMIF('Cleaned Data'!$D$2:$D$161,A13,'Cleaned Data'!$H$2:$H$161) -> 10
... A17: UltraSlim 14 | B17: Laptops | C17: =SUMIF('Cleaned Data'!$D$2:$D$161,A17,'Cleaned Data'!$I$2:$I$161) -> 11520 | D17: =SUMIF('Cleaned Data'!$D$2:$D$161,A17,'Cleaned Data'!$G$2:$G$161) -> 2723.09 | E17: =SUMIF('Cleaned Data'!$D$2:$D$161,A17,'Cleaned Data'!$H$2:$H$161) -> 16

Sheet Pivot - Monthly Trend
A1: Month | B1: Total Sales | C1: Total Profit
A2: 2026-01 | B2: =SUMPRODUCT((TEXT('Cleaned Data'!$B$2:$B$161,"yyyy-mm")=A2)*'Cleaned Data'!$I$2:$I$161) -> 31977 | C2: =SUMPRODUCT((TEXT('Cleaned Data'!$B$2:$B$161,"yyyy-mm")=A2)*'Cleaned Data'!$G$2:$G$161) -> 8380.04
A3: 2026-02 | B3: =SUMPRODUCT((TEXT('Cleaned Data'!$B$2:$B$161,"yyyy-mm")=A3)*'Cleaned Data'!$I$2:$I$161) -> 24055 | C3: =SUMPRODUCT((TEXT('Cleaned Data'!$B$2:$B$161,"yyyy-mm")=A3)*'Cleaned Data'!$G$2:$G$161) -> 6915.37
A4: 2026-03 | B4: =SUMPRODUCT((TEXT('Cleaned Data'!$B$2:$B$161,"yyyy-mm")=A4)*'Cleaned Data'!$I$2:$I$161) -> 15852 | C4: =SUMPRODUCT((TEXT('Cleaned Data'!$B$2:$B$161,"yyyy-mm")=A4)*'Cleaned Data'!$G$2:$G$161) -> 3894.82
A5: 2026-04 | B5: =SUMPRODUCT((TEXT('Cleaned Data'!$B$2:$B$161,"yyyy-mm")=A5)*'Cleaned Data'!$I$2:$I$161) -> 28879 | C5: =SUMPRODUCT((TEXT('Cleaned Data'!$B$2:$B$161,"yyyy-mm")=A5)*'Cleaned Data'!$G$2:$G$161) -> 7190.46
A6: 2026-05 | B6: =SUMPRODUCT((TEXT('Cleaned Data'!$B$2:$B$161,"yyyy-mm")=A6)*'Cleaned Data'!$I$2:$I$161) -> 40366 | C6: =SUMPRODUCT((TEXT('Cleaned Data'!$B$2:$B$161,"yyyy-mm")=A6)*'Cleaned Data'!$G$2:$G$161) -> 10658.84
A7: 2026-06 | B7: =SUMPRODUCT((TEXT('Cleaned Data'!$B$2:$B$161,"yyyy-mm")=A7)*'Cleaned Data'!$I$2:$I$161) -> 30155 | C7: =SUMPRODUCT((TEXT('Cleaned Data'!$B$2:$B$161,"yyyy-mm")=A7)*'Cleaned Data'!$G$2:$G$161) -> 6508.42
